rl_opts/__init__.py
rl_opts/_modidx.py
rl_opts/analytics.py
rl_opts/imitation.py
rl_opts/learn_and_bench.py
rl_opts/mfpt.py
rl_opts/rl_framework_numba.py
rl_opts/utils.py
rl_opts/rl_framework/__init__.py
rl_opts/rl_framework/legacy.py
rl_opts/rl_framework/numba/__init__.py
rl_opts/rl_framework/numba/agents.py
rl_opts/rl_framework/numba/environments.py
rl_opts-0.2.0.dist-info/METADATA
rl_opts-0.2.0.dist-info/WHEEL
rl_opts-0.2.0.dist-info/entry_points.txt
rl_opts-0.2.0.dist-info/top_level.txt
rl_opts-0.2.0.dist-info/RECORD
