Metadata-Version: 2.1
Name: rl-opts
Version: 0.2.0
Summary: Reinforcement Learning of Optimal Search strategies
Home-page: https://github.com/gorkamunoz/rl_opts/
Author: Gorka Muñoz-Gil
Author-email: munoz.gil.gorka@gmail.com
License: Apache Software License 2.0
Keywords: Reiforcement learning,optimal search,foraging,Physics
Classifier: Development Status :: 3 - Alpha
Classifier: Intended Audience :: Developers
Classifier: Natural Language :: English
Classifier: Programming Language :: Python :: 3.8
Classifier: Programming Language :: Python :: 3.9
Classifier: Programming Language :: Python :: 3.10
Classifier: License :: OSI Approved :: Apache Software License
Requires-Python: >=3.8
Requires-Dist: numpy
Requires-Dist: scipy
Requires-Dist: matplotlib
Requires-Dist: tqdm
Requires-Dist: pandas
Requires-Dist: numba
Requires-Dist: joblib
Provides-Extra: dev
